massphotometry/__init__.py
massphotometry/metadata.py
massphotometry/read.py
massphotometry-0.1.0.dist-info/licenses/LICENSE
massphotometry-0.1.0.dist-info/METADATA
massphotometry-0.1.0.dist-info/WHEEL
massphotometry-0.1.0.dist-info/top_level.txt
massphotometry-0.1.0.dist-info/RECORD
