Metadata-Version: 2.4
Name: massphotometry
Version: 0.1.0
Summary: Python package for mass photometry data analysis - MP file reading and metadata handling
Author-email: Jan Christoph Thiele <jan.thiele@chem.ox.ac.uk>, Stephen Thorpe <stephen.thorpe@chem.ox.ac.uk>
License: MIT License
Project-URL: Homepage, https://github.com/thielec/massphotometry
Project-URL: Bug Tracker, https://github.com/thielec/massphotometry/issues
Keywords: mass photometry,single molecule,microscopy,data analysis
Requires-Python: >=3.10
License-File: LICENSE
Requires-Dist: numpy
Requires-Dist: h5py
Requires-Dist: hdf5plugin
Provides-Extra: dev
Requires-Dist: pytest; extra == "dev"
Requires-Dist: black; extra == "dev"
Requires-Dist: flake8; extra == "dev"
Requires-Dist: mypy; extra == "dev"
Requires-Dist: pre-commit; extra == "dev"
Dynamic: license-file
